wyoming_mlx_whisper/__init__.py
wyoming_mlx_whisper/__main__.py
wyoming_mlx_whisper/_version.py
wyoming_mlx_whisper/const.py
wyoming_mlx_whisper/handler.py
wyoming_mlx_whisper/server.py
wyoming_mlx_whisper-1.4.0.dist-info/METADATA
wyoming_mlx_whisper-1.4.0.dist-info/WHEEL
wyoming_mlx_whisper-1.4.0.dist-info/entry_points.txt
wyoming_mlx_whisper-1.4.0.dist-info/licenses/LICENSE
wyoming_mlx_whisper-1.4.0.dist-info/RECORD
