Metadata-Version: 2.4
Name: wyoming-mlx-whisper
Version: 1.4.0
Summary: Wyoming Server for MLX whisper
Project-URL: Homepage, https://github.com/basnijholt/wyoming-mlx-whisper
Project-URL: Repository, https://github.com/basnijholt/wyoming-mlx-whisper.git
Author: Vincent Lin
Author-email: Bas Nijholt <bas@nijholt.com>
License-Expression: MIT
License-File: LICENSE
Keywords: mlx,rhasspy,stt,whisper,wyoming
Classifier: Development Status :: 3 - Alpha
Classifier: Intended Audience :: Developers
Classifier: License :: OSI Approved :: MIT License
Classifier: Programming Language :: Python :: 3.10
Classifier: Programming Language :: Python :: 3.11
Classifier: Programming Language :: Python :: 3.12
Classifier: Programming Language :: Python :: 3.13
Classifier: Topic :: Text Processing :: Linguistic
Requires-Python: <3.14,>=3.10
Requires-Dist: mlx-whisper
Requires-Dist: numpy
Requires-Dist: rich
Requires-Dist: typer
Requires-Dist: wyoming
Provides-Extra: dev
Requires-Dist: mypy; extra == 'dev'
Requires-Dist: pre-commit; extra == 'dev'
Requires-Dist: pytest; extra == 'dev'
Requires-Dist: pytest-asyncio; extra == 'dev'
Requires-Dist: pytest-cov; extra == 'dev'
Requires-Dist: ruff; extra == 'dev'
